azure_datalake_utils/__init__.py
azure_datalake_utils/azure_datalake_utils.py
azure_datalake_utils/exepctions.py
azure_datalake_utils/experimental.py
azure_datalake_utils/partitions.py
azure_datalake_utils/storage_account_utils.py
azure_datalake_utils-0.5.10.dist-info/LICENSE
azure_datalake_utils-0.5.10.dist-info/METADATA
azure_datalake_utils-0.5.10.dist-info/WHEEL
azure_datalake_utils-0.5.10.dist-info/RECORD
