Metadata-Version: 2.1
Name: azure_datalake_utils
Version: 0.5.10
Summary: Utilidades para interactuar con Azure Datalake.
Home-page: https://github.com/centraal-api/azure-datalake-utils
License: Apache-2.0
Author: centraal.studio
Author-email: equipo@centraal.studio
Requires-Python: >=3.8,<4.0
Classifier: Development Status :: 2 - Pre-Alpha
Classifier: Intended Audience :: Developers
Classifier: License :: OSI Approved :: Apache Software License
Classifier: Natural Language :: English
Classifier: Programming Language :: Python :: 3
Classifier: Programming Language :: Python :: 3.8
Classifier: Programming Language :: Python :: 3.9
Classifier: Programming Language :: Python :: 3.10
Classifier: Programming Language :: Python :: 3.11
Classifier: Programming Language :: Python :: 3.12
Provides-Extra: dev
Provides-Extra: doc
Provides-Extra: test
Requires-Dist: Jinja2 (>=2.11.1,<3.0) ; extra == "test"
Requires-Dist: adlfs (<=2023.12.0)
Requires-Dist: azure-identity (>=1.10.0,<2.0.0)
Requires-Dist: black (>=22.3.0,<23.0.0) ; extra == "test"
Requires-Dist: bump2version (>=1.0.1,<2.0.0) ; extra == "dev"
Requires-Dist: click (>=8.0.2,<9.0.0)
Requires-Dist: flake8 (>=3.9.2,<4.0.0) ; extra == "test"
Requires-Dist: flake8-docstrings (>=1.6.0,<2.0.0) ; extra == "test"
Requires-Dist: fsspec (<=2023.9.0)
Requires-Dist: griffe[python] (<=0.29.1)
Requires-Dist: ipykernel (>=6.15.2,<7.0.0) ; extra == "test"
Requires-Dist: isort (>=5.8.0,<6.0.0) ; extra == "test"
Requires-Dist: markupsafe (==2.0.1) ; extra == "test"
Requires-Dist: mkdocs (<=1.4.2) ; extra == "doc"
Requires-Dist: mkdocs-autorefs (>=0.3,<0.4) ; extra == "doc"
Requires-Dist: mkdocs-include-markdown-plugin (>=1.0.0,<2.0.0) ; extra == "doc"
Requires-Dist: mkdocs-material (>=8.0,<9.0) ; extra == "doc"
Requires-Dist: mkdocs-material-extensions (<=1.1.1)
Requires-Dist: mkdocstrings[python] (>=0.19.0,<0.20.0) ; extra == "doc"
Requires-Dist: openpyxl (>=3.0.10,<4.0.0)
Requires-Dist: pandas (<=2.0.3)
Requires-Dist: pip (>=22.0) ; extra == "dev"
Requires-Dist: pre-commit (>=2.12.0,<3.0.0) ; extra == "dev"
Requires-Dist: pyarrow (<=14.0.2)
Requires-Dist: pytest (>=6.2.4,<7.0.0) ; extra == "test"
Requires-Dist: pytest-cov (>=2.12.0,<3.0.0) ; extra == "test"
Requires-Dist: toml (>=0.10.2,<0.11.0) ; extra == "dev"
Requires-Dist: tox (>=3.20.1,<4.0.0) ; extra == "dev"
Requires-Dist: twine (>=3.3.0,<4.0.0) ; extra == "dev"
Requires-Dist: virtualenv (>=20.2.2,<21.0.0) ; extra == "dev"
